OpenImageTokenizer/__init__.py
OpenImageTokenizer/configs.py
OpenImageTokenizer/configs_samples.py
OpenImageTokenizer/hf_utils.py
OpenImageTokenizer/samples.py
OpenImageTokenizer/tokenizers.py
OpenImageTokenizer/IBQ/__init__.py
OpenImageTokenizer/IBQ/lr_scheduler.py
OpenImageTokenizer/IBQ/util.py
OpenImageTokenizer/IBQ/data/__init__.py
OpenImageTokenizer/IBQ/data/base.py
OpenImageTokenizer/IBQ/data/helper_types.py
OpenImageTokenizer/IBQ/data/imagenet.py
OpenImageTokenizer/IBQ/data/utils.py
OpenImageTokenizer/IBQ/models/__init__.py
OpenImageTokenizer/IBQ/models/cond_transformer_llama.py
OpenImageTokenizer/IBQ/models/dummy_cond_stage.py
OpenImageTokenizer/IBQ/models/ibqgan.py
OpenImageTokenizer/IBQ/models/ibqgan_pretrain.py
OpenImageTokenizer/IBQ/models/main.py
OpenImageTokenizer/IBQ/modules/ema.py
OpenImageTokenizer/IBQ/modules/util.py
OpenImageTokenizer/IBQ/modules/autoencoder/lpips/vgg.pth
OpenImageTokenizer/IBQ/modules/diffusionmodules/__init__.py
OpenImageTokenizer/IBQ/modules/diffusionmodules/model.py
OpenImageTokenizer/IBQ/modules/discriminator/__init__.py
OpenImageTokenizer/IBQ/modules/discriminator/model.py
OpenImageTokenizer/IBQ/modules/losses/__init__.py
OpenImageTokenizer/IBQ/modules/losses/lpips.py
OpenImageTokenizer/IBQ/modules/losses/segmentation.py
OpenImageTokenizer/IBQ/modules/losses/vqperceptual.py
OpenImageTokenizer/IBQ/modules/scheduler/__init__.py
OpenImageTokenizer/IBQ/modules/scheduler/lr_scheduler.py
OpenImageTokenizer/IBQ/modules/transformer/__init__.py
OpenImageTokenizer/IBQ/modules/transformer/llama.py
OpenImageTokenizer/IBQ/modules/transformer/mingpt.py
OpenImageTokenizer/IBQ/modules/transformer/permuter.py
OpenImageTokenizer/IBQ/modules/vqvae/__init__.py
OpenImageTokenizer/IBQ/modules/vqvae/quantize.py
OpenImageTokenizer/Open_MAGVIT2/__init__.py
OpenImageTokenizer/Open_MAGVIT2/lr_scheduler.py
OpenImageTokenizer/Open_MAGVIT2/util.py
OpenImageTokenizer/Open_MAGVIT2/data/__init__.py
OpenImageTokenizer/Open_MAGVIT2/data/base.py
openimagetokenizer-0.1.5.dist-info/METADATA
openimagetokenizer-0.1.5.dist-info/WHEEL
openimagetokenizer-0.1.5.dist-info/licenses/LICENSE
openimagetokenizer-0.1.5.dist-info/RECORD
