Metadata-Version: 2.4
Name: OpenImageTokenizer
Version: 0.1.5
Summary: OpenImageTokenizer: Based in SEED-Voken A Series of Powerful Visual Tokenizers
Author-email: "Rivera.ai/Fredy Rivera" <riveraaai200678@gmail.com>
License-File: LICENSE
Requires-Python: >=3.8
